fui_web/__init__.py
fui_web/fastapi/__init__.py
fui_web/fastapi/app.py
fui_web/fastapi/fui_app.py
fui_web/fastapi/fui_app_manager.py
fui_web/fastapi/fui_fastapi.py
fui_web/fastapi/fui_oauth.py
fui_web/fastapi/fui_static_files.py
fui_web/fastapi/fui_upload.py
fui_web/fastapi/oauth_state.py
fui_web/fastapi/serve_fastapi_web_app.py
fui_web/patch_index.py
fui_web/uploads.py
fui_web/version.py
fui_web/web/.last_build_id
fui_web/web/assets/AssetManifest.bin
fui_web/web/assets/AssetManifest.bin.json
fui_web/web/assets/AssetManifest.json
fui_web/web/assets/FontManifest.json
fui_web/web/assets/fonts/MaterialIcons-Regular.otf
fui_web/web/assets/NOTICES
fui_web/web/assets/packages/cupertino_icons/assets/CupertinoIcons.ttf
fui_web/web/assets/packages/flutter_map/lib/assets/flutter_map_logo.png
fui_web/web/assets/packages/media_kit/assets/web/hls1.4.10.js
fui_web/web/assets/packages/record_web/assets/js/record.fixwebmduration.js
fui_web/web/assets/packages/record_web/assets/js/record.worklet.js
fui_web/web/assets/packages/wakelock_plus/assets/no_sleep.js
fui_web/web/assets/shaders/ink_sparkle.frag
fui_web/web/canvaskit/canvaskit.js
fui_web/web/canvaskit/canvaskit.js.symbols
fui_web/web/canvaskit/canvaskit.wasm
fui_web/web/canvaskit/chromium/canvaskit.js
fui_web/web/canvaskit/chromium/canvaskit.js.symbols
fui_web/web/canvaskit/chromium/canvaskit.wasm
fui_web/web/canvaskit/skwasm.js
fui_web/web/canvaskit/skwasm.js.symbols
fui_web/web/canvaskit/skwasm.wasm
fui_web/web/canvaskit/skwasm.worker.js
fui_web/web/favicon.png
fui_web/web/flutter.js
fui_web/web/flutter_bootstrap.js
fui_web/web/flutter_service_worker.js
fui_web/web/icons/apple-touch-icon-192.png
fui_web/web/icons/icon-192.png
fui_web/web/icons/icon-512.png
fui_web/web/icons/icon-maskable-192.png
fui_web/web/icons/icon-maskable-512.png
fui_web/web/icons/loading-animation.png
fui_web/web/index.html
fui_web/web/main.dart.js
fui_web/web/manifest.json
fui_web/web/python-worker.js
fui_web/web/python.js
fui_web/web/version.json
fui_web-1.0.0.dist-info/METADATA
fui_web-1.0.0.dist-info/WHEEL
fui_web-1.0.0.dist-info/RECORD
