Metadata-Version: 2.3
Name: fui-web
Version: 1.0.0
Summary: fui web client in Flutter.
License: Apache-2.0
Author: Appveyor Systems Inc.
Author-email: hello@fui.dev
Requires-Python: >=3.8,<4.0
Classifier: License :: OSI Approved :: Apache Software License
Classifier: Programming Language :: Python :: 3
Classifier: Programming Language :: Python :: 3.8
Classifier: Programming Language :: Python :: 3.9
Classifier: Programming Language :: Python :: 3.10
Classifier: Programming Language :: Python :: 3.11
Classifier: Programming Language :: Python :: 3.12
Classifier: Programming Language :: Python :: 3.13
Requires-Dist: fastapi
Requires-Dist: fui (==1.0.0)
Requires-Dist: uvicorn[standard]
Project-URL: documentation, https://fui.dev/docs
Project-URL: homepage, https://fui.dev
Project-URL: repository, https://github.com/fui-dev/fui
